horseshit-0.0.5.dist-info/top_level.txt
horseshit-0.0.5.dist-info/metadata.json
horseshit-0.0.5.dist-info/DESCRIPTION.rst
horseshit-0.0.5.dist-info/METADATA
horseshit-0.0.5.dist-info/RECORD
horseshit-0.0.5.dist-info/WHEEL
horseshit-0.0.5.dist-info/entry_points.txt
horseshit/version.py
horseshit/__init__.py
horseshit/main.py
